jupyter_retext_language_server/__init__.py
jupyter_retext_language_server/config.py
jupyter_retext_language_server/plugins.py
jupyter_retext_language_server/specs.py
jupyter_retext_language_server/utils.py
jupyter_retext_language_server/schemas/__init__.py
jupyter_retext_language_server/schemas/config.schema.json
jupyter_retext_language_server-1.0.1.data/data/etc/jupyter/jupyter_server_config.d/jupyter_retext_language_server.json
jupyter_retext_language_server-1.0.1.data/data/share/jupyter-retext-language-server/bin/retext-spell.cjs
jupyter_retext_language_server-1.0.1.data/data/share/jupyter-retext-language-server/bin/server.cjs
jupyter_retext_language_server-1.0.1.dist-info/METADATA
jupyter_retext_language_server-1.0.1.dist-info/WHEEL
jupyter_retext_language_server-1.0.1.dist-info/entry_points.txt
jupyter_retext_language_server-1.0.1.dist-info/RECORD
