Metadata-Version: 2.4
Name: jupyter-retext-language-server
Version: 1.0.1
Summary: A language server for Markdown documents that supports retext plugins
Requires-Dist: jupyter-lsp
Requires-Dist: traitlets
